{
    "result": {
        "players": [
            {
                "account_id": 4294967295,
                "player_slot": 0,
                "team_number": 0,
                "team_slot": 0,
                "hero_id": 7,
                "item_0": 1,
                "item_1": 214,
                "item_2": 36,
                "item_3": 244,
                "item_4": 57,
                "item_5": 265,
                "backpack_0": 0,
                "backpack_1": 0,
                "backpack_2": 0,
                "item_neutral": 834,
                "kills": 7,
                "deaths": 13,
                "assists": 15,
                "leaver_status": 0,
                "last_hits": 15,
                "denies": 1,
                "gold_per_min": 283,
                "xp_per_min": 316,
                "level": 14,
                "net_worth": 7532,
                "aghanims_scepter": 0,
                "aghanims_shard": 1,
                "moonshard": 0,
                "hero_damage": 12554,
                "tower_damage": 1077,
                "hero_healing": 390,
                "gold": 1107,
                "gold_spent": 8690,
                "scaled_hero_damage": 8807,
                "scaled_tower_damage": 396,
                "scaled_hero_healing": 133,
                "ability_upgrades": [
                    {
                        "ability": 5023,
                        "time": 243,
                        "level": 1
                    },
                    {
                        "ability": 5024,
                        "time": 343,
                        "level": 2
                    },
                    {
                        "ability": 5023,
                        "time": 471,
                        "level": 3
                    },
                    {
                        "ability": 5025,
                        "time": 602,
                        "level": 4
                    },
                    {
                        "ability": 5023,
                        "time": 884,
                        "level": 5
                    },
                    {
                        "ability": 5026,
                        "time": 892,
                        "level": 6
                    },
                    {
                        "ability": 5023,
                        "time": 1082,
                        "level": 7
                    },
                    {
                        "ability": 5025,
                        "time": 1334,
                        "level": 8
                    },
                    {
                        "ability": 5025,
                        "time": 1477,
                        "level": 9
                    },
                    {
                        "ability": 5025,
                        "time": 1507,
                        "level": 10
                    },
                    {
                        "ability": 5024,
                        "time": 1552,
                        "level": 11
                    },
                    {
                        "ability": 5026,
                        "time": 1677,
                        "level": 12
                    },
                    {
                        "ability": 744,
                        "time": 1784,
                        "level": 13
                    }
                ]
            },
            {
                "account_id": 4294967295,
                "player_slot": 1,
                "team_number": 0,
                "team_slot": 1,
                "hero_id": 13,
                "item_0": 273,
                "item_1": 168,
                "item_2": 1,
                "item_3": 63,
                "item_4": 534,
                "item_5": 116,
                "backpack_0": 0,
                "backpack_1": 0,
                "backpack_2": 0,
                "item_neutral": 361,
                "kills": 19,
                "deaths": 4,
                "assists": 16,
                "leaver_status": 0,
                "last_hits": 226,
                "denies": 2,
                "gold_per_min": 625,
                "xp_per_min": 859,
                "level": 24,
                "net_worth": 18709,
                "aghanims_scepter": 0,
                "aghanims_shard": 0,
                "moonshard": 0,
                "hero_damage": 47035,
                "tower_damage": 1655,
                "hero_healing": 191,
                "gold": 709,
                "gold_spent": 20510,
                "scaled_hero_damage": 28940,
                "scaled_tower_damage": 512,
                "scaled_hero_healing": 68,
                "ability_upgrades": [
                    {
                        "ability": 5069,
                        "time": 134,
                        "level": 1
                    },
                    {
                        "ability": 5071,
                        "time": 292,
                        "level": 2
                    },
                    {
                        "ability": 5069,
                        "time": 354,
                        "level": 3
                    },
                    {
                        "ability": 5071,
                        "time": 404,
                        "level": 4
                    },
                    {
                        "ability": 5069,
                        "time": 492,
                        "level": 5
                    },
                    {
                        "ability": 5073,
                        "time": 538,
                        "level": 6
                    },
                    {
                        "ability": 5069,
                        "time": 630,
                        "level": 7
                    },
                    {
                        "ability": 5072,
                        "time": 726,
                        "level": 8
                    },
                    {
                        "ability": 5071,
                        "time": 777,
                        "level": 9
                    },
                    {
                        "ability": 5071,
                        "time": 884,
                        "level": 10
                    },
                    {
                        "ability": 5072,
                        "time": 934,
                        "level": 11
                    },
                    {
                        "ability": 5072,
                        "time": 1089,
                        "level": 12
                    },
                    {
                        "ability": 5072,
                        "time": 1140,
                        "level": 13
                    },
                    {
                        "ability": 5073,
                        "time": 1246,
                        "level": 14
                    },
                    {
                        "ability": 407,
                        "time": 1388,
                        "level": 15
                    },
                    {
                        "ability": 797,
                        "time": 1516,
                        "level": 16
                    },
                    {
                        "ability": 5073,
                        "time": 1630,
                        "level": 17
                    },
                    {
                        "ability": 6402,
                        "time": 1837,
                        "level": 18
                    }
                ]
            },
            {
                "account_id": 4294967295,
                "player_slot": 2,
                "team_number": 0,
                "team_slot": 2,
                "hero_id": 112,
                "item_0": 218,
                "item_1": 1,
                "item_2": 188,
                "item_3": 232,
                "item_4": 214,
                "item_5": 34,
                "backpack_0": 0,
                "backpack_1": 28,
                "backpack_2": 0,
                "item_neutral": 376,
                "kills": 3,
                "deaths": 4,
                "assists": 24,
                "leaver_status": 0,
                "last_hits": 71,
                "denies": 6,
                "gold_per_min": 332,
                "xp_per_min": 442,
                "level": 17,
                "net_worth": 8376,
                "aghanims_scepter": 0,
                "aghanims_shard": 1,
                "moonshard": 0,
                "hero_damage": 16046,
                "tower_damage": 49,
                "hero_healing": 7759,
                "gold": 51,
                "gold_spent": 10180,
                "scaled_hero_damage": 12174,
                "scaled_tower_damage": 13,
                "scaled_hero_healing": 4258,
                "ability_upgrades": [
                    {
                        "ability": 5651,
                        "time": 174,
                        "level": 1
                    },
                    {
                        "ability": 5652,
                        "time": 325,
                        "level": 2
                    },
                    {
                        "ability": 5652,
                        "time": 457,
                        "level": 3
                    },
                    {
                        "ability": 5651,
                        "time": 558,
                        "level": 4
                    },
                    {
                        "ability": 5652,
                        "time": 752,
                        "level": 5
                    },
                    {
                        "ability": 5654,
                        "time": 853,
                        "level": 6
                    },
                    {
                        "ability": 5652,
                        "time": 1015,
                        "level": 7
                    },
                    {
                        "ability": 5653,
                        "time": 1112,
                        "level": 8
                    },
                    {
                        "ability": 5653,
                        "time": 1208,
                        "level": 9
                    },
                    {
                        "ability": 5653,
                        "time": 1345,
                        "level": 10
                    },
                    {
                        "ability": 5653,
                        "time": 1511,
                        "level": 11
                    },
                    {
                        "ability": 5654,
                        "time": 1576,
                        "level": 12
                    },
                    {
                        "ability": 418,
                        "time": 1699,
                        "level": 13
                    },
                    {
                        "ability": 5651,
                        "time": 1772,
                        "level": 14
                    },
                    {
                        "ability": 6297,
                        "time": 1896,
                        "level": 15
                    },
                    {
                        "ability": 5651,
                        "time": 1985,
                        "level": 16
                    }
                ]
            },
            {
                "account_id": 4294967295,
                "player_slot": 3,
                "team_number": 0,
                "team_slot": 3,
                "hero_id": 58,
                "item_0": 63,
                "item_1": 36,
                "item_2": 263,
                "item_3": 247,
                "item_4": 77,
                "item_5": 88,
                "backpack_0": 0,
                "backpack_1": 237,
                "backpack_2": 43,
                "item_neutral": 212,
                "kills": 7,
                "deaths": 1,
                "assists": 20,
                "leaver_status": 0,
                "last_hits": 139,
                "denies": 16,
                "gold_per_min": 449,
                "xp_per_min": 632,
                "level": 21,
                "net_worth": 14509,
                "aghanims_scepter": 0,
                "aghanims_shard": 0,
                "moonshard": 0,
                "hero_damage": 35368,
                "tower_damage": 11296,
                "hero_healing": 3338,
                "gold": 1984,
                "gold_spent": 13810,
                "scaled_hero_damage": 21793,
                "scaled_tower_damage": 4358,
                "scaled_hero_healing": 1026,
                "ability_upgrades": [
                    {
                        "ability": 5270,
                        "time": 276,
                        "level": 1
                    },
                    {
                        "ability": 5268,
                        "time": 323,
                        "level": 2
                    },
                    {
                        "ability": 5270,
                        "time": 359,
                        "level": 3
                    },
                    {
                        "ability": 5269,
                        "time": 467,
                        "level": 4
                    },
                    {
                        "ability": 5270,
                        "time": 549,
                        "level": 5
                    },
                    {
                        "ability": 5267,
                        "time": 592,
                        "level": 6
                    },
                    {
                        "ability": 5270,
                        "time": 644,
                        "level": 7
                    },
                    {
                        "ability": 5269,
                        "time": 694,
                        "level": 8
                    },
                    {
                        "ability": 5269,
                        "time": 801,
                        "level": 9
                    },
                    {
                        "ability": 5937,
                        "time": 1047,
                        "level": 10
                    },
                    {
                        "ability": 5269,
                        "time": 1112,
                        "level": 11
                    },
                    {
                        "ability": 5267,
                        "time": 1238,
                        "level": 12
                    },
                    {
                        "ability": 5268,
                        "time": 1325,
                        "level": 13
                    },
                    {
                        "ability": 5268,
                        "time": 1461,
                        "level": 14
                    },
                    {
                        "ability": 6086,
                        "time": 1515,
                        "level": 15
                    },
                    {
                        "ability": 5268,
                        "time": 1635,
                        "level": 16
                    },
                    {
                        "ability": 5267,
                        "time": 1771,
                        "level": 17
                    },
                    {
                        "ability": 6379,
                        "time": 2133,
                        "level": 18
                    }
                ]
            },
            {
                "account_id": 4294967295,
                "player_slot": 4,
                "team_number": 0,
                "team_slot": 4,
                "hero_id": 41,
                "item_0": 63,
                "item_1": 116,
                "item_2": 185,
                "item_3": 30,
                "item_4": 158,
                "item_5": 65,
                "backpack_0": 11,
                "backpack_1": 36,
                "backpack_2": 0,
                "item_neutral": 306,
                "kills": 13,
                "deaths": 3,
                "assists": 15,
                "leaver_status": 0,
                "last_hits": 192,
                "denies": 31,
                "gold_per_min": 609,
                "xp_per_min": 835,
                "level": 24,
                "net_worth": 17756,
                "aghanims_scepter": 0,
                "aghanims_shard": 1,
                "moonshard": 0,
                "hero_damage": 17241,
                "tower_damage": 6347,
                "hero_healing": 0,
                "gold": 656,
                "gold_spent": 17570,
                "scaled_hero_damage": 12365,
                "scaled_tower_damage": 2151,
                "scaled_hero_healing": 0,
                "ability_upgrades": [
                    {
                        "ability": 5691,
                        "time": 221,
                        "level": 1
                    },
                    {
                        "ability": 5182,
                        "time": 320,
                        "level": 2
                    },
                    {
                        "ability": 5184,
                        "time": 400,
                        "level": 3
                    },
                    {
                        "ability": 5184,
                        "time": 506,
                        "level": 4
                    },
                    {
                        "ability": 5182,
                        "time": 601,
                        "level": 5
                    },
                    {
                        "ability": 5185,
                        "time": 664,
                        "level": 6
                    },
                    {
                        "ability": 5182,
                        "time": 741,
                        "level": 7
                    },
                    {
                        "ability": 5182,
                        "time": 846,
                        "level": 8
                    },
                    {
                        "ability": 5184,
                        "time": 937,
                        "level": 9
                    },
                    {
                        "ability": 5184,
                        "time": 1018,
                        "level": 10
                    },
                    {
                        "ability": 730,
                        "time": 1113,
                        "level": 11
                    },
                    {
                        "ability": 730,
                        "time": 1180,
                        "level": 12
                    },
                    {
                        "ability": 730,
                        "time": 1251,
                        "level": 13
                    },
                    {
                        "ability": 5691,
                        "time": 1282,
                        "level": 14
                    },
                    {
                        "ability": 7388,
                        "time": 1400,
                        "level": 15
                    },
                    {
                        "ability": 730,
                        "time": 1575,
                        "level": 16
                    },
                    {
                        "ability": 730,
                        "time": 1679,
                        "level": 17
                    },
                    {
                        "ability": 5691,
                        "time": 1734,
                        "level": 18
                    },
                    {
                        "ability": 730,
                        "time": 1827,
                        "level": 19
                    },
                    {
                        "ability": 6128,
                        "time": 2006,
                        "level": 20
                    },
                    {
                        "ability": 5691,
                        "time": 2085,
                        "level": 21
                    },
                    {
                        "ability": 730,
                        "time": 2123,
                        "level": 22
                    },
                    {
                        "ability": 867,
                        "time": 2124,
                        "level": 23
                    },
                    {
                        "ability": 5185,
                        "time": 2125,
                        "level": 24
                    }
                ]
            },
            {
                "account_id": 872008996,
                "player_slot": 128,
                "team_number": 1,
                "team_slot": 0,
                "hero_id": 126,
                "item_0": 29,
                "item_1": 36,
                "item_2": 273,
                "item_3": 41,
                "item_4": 116,
                "item_5": 43,
                "backpack_0": 38,
                "backpack_1": 11,
                "backpack_2": 0,
                "item_neutral": 357,
                "kills": 10,
                "deaths": 6,
                "assists": 4,
                "leaver_status": 0,
                "last_hits": 173,
                "denies": 9,
                "gold_per_min": 474,
                "xp_per_min": 673,
                "level": 22,
                "net_worth": 15963,
                "aghanims_scepter": 1,
                "aghanims_shard": 1,
                "moonshard": 0,
                "hero_damage": 20916,
                "tower_damage": 31,
                "hero_healing": 0,
                "gold": 288,
                "gold_spent": 17335,
                "scaled_hero_damage": 13686,
                "scaled_tower_damage": 25,
                "scaled_hero_healing": 0,
                "ability_upgrades": [
                    {
                        "ability": 7710,
                        "time": 253,
                        "level": 1
                    },
                    {
                        "ability": 7701,
                        "time": 274,
                        "level": 2
                    },
                    {
                        "ability": 7710,
                        "time": 324,
                        "level": 3
                    },
                    {
                        "ability": 7701,
                        "time": 378,
                        "level": 4
                    },
                    {
                        "ability": 7710,
                        "time": 450,
                        "level": 5
                    },
                    {
                        "ability": 7705,
                        "time": 534,
                        "level": 6
                    },
                    {
                        "ability": 7710,
                        "time": 611,
                        "level": 7
                    },
                    {
                        "ability": 7701,
                        "time": 685,
                        "level": 8
                    },
                    {
                        "ability": 7701,
                        "time": 769,
                        "level": 9
                    },
                    {
                        "ability": 6470,
                        "time": 873,
                        "level": 10
                    },
                    {
                        "ability": 6470,
                        "time": 901,
                        "level": 11
                    },
                    {
                        "ability": 7705,
                        "time": 1093,
                        "level": 12
                    },
                    {
                        "ability": 6470,
                        "time": 1176,
                        "level": 13
                    },
                    {
                        "ability": 6470,
                        "time": 1209,
                        "level": 14
                    },
                    {
                        "ability": 7709,
                        "time": 1272,
                        "level": 15
                    },
                    {
                        "ability": 7707,
                        "time": 1511,
                        "level": 16
                    },
                    {
                        "ability": 7705,
                        "time": 1636,
                        "level": 17
                    },
                    {
                        "ability": 6326,
                        "time": 1994,
                        "level": 18
                    }
                ]
            },
            {
                "account_id": 4294967295,
                "player_slot": 129,
                "team_number": 1,
                "team_slot": 1,
                "hero_id": 26,
                "item_0": 1,
                "item_1": 36,
                "item_2": 43,
                "item_3": 593,
                "item_4": 593,
                "item_5": 214,
                "backpack_0": 0,
                "backpack_1": 0,
                "backpack_2": 0,
                "item_neutral": 290,
                "kills": 1,
                "deaths": 15,
                "assists": 10,
                "leaver_status": 0,
                "last_hits": 29,
                "denies": 3,
                "gold_per_min": 256,
                "xp_per_min": 276,
                "level": 13,
                "net_worth": 6155,
                "aghanims_scepter": 0,
                "aghanims_shard": 1,
                "moonshard": 0,
                "hero_damage": 7640,
                "tower_damage": 0,
                "hero_healing": 195,
                "gold": 580,
                "gold_spent": 6975,
                "scaled_hero_damage": 6076,
                "scaled_tower_damage": 0,
                "scaled_hero_healing": 221,
                "ability_upgrades": [
                    {
                        "ability": 5044,
                        "time": 192,
                        "level": 1
                    },
                    {
                        "ability": 5046,
                        "time": 403,
                        "level": 2
                    },
                    {
                        "ability": 5045,
                        "time": 464,
                        "level": 3
                    },
                    {
                        "ability": 5044,
                        "time": 703,
                        "level": 4
                    },
                    {
                        "ability": 5044,
                        "time": 755,
                        "level": 5
                    },
                    {
                        "ability": 5047,
                        "time": 847,
                        "level": 6
                    },
                    {
                        "ability": 5044,
                        "time": 981,
                        "level": 7
                    },
                    {
                        "ability": 5046,
                        "time": 1209,
                        "level": 8
                    },
                    {
                        "ability": 5046,
                        "time": 1245,
                        "level": 9
                    },
                    {
                        "ability": 5046,
                        "time": 1612,
                        "level": 10
                    },
                    {
                        "ability": 5045,
                        "time": 1718,
                        "level": 11
                    },
                    {
                        "ability": 5047,
                        "time": 1819,
                        "level": 12
                    },
                    {
                        "ability": 5045,
                        "time": 2066,
                        "level": 13
                    }
                ]
            },
            {
                "account_id": 4294967295,
                "player_slot": 130,
                "team_number": 1,
                "team_slot": 2,
                "hero_id": 73,
                "item_0": 43,
                "item_1": 34,
                "item_2": 21,
                "item_3": 214,
                "item_4": 0,
                "item_5": 244,
                "backpack_0": 0,
                "backpack_1": 0,
                "backpack_2": 0,
                "item_neutral": 834,
                "kills": 1,
                "deaths": 10,
                "assists": 10,
                "leaver_status": 0,
                "last_hits": 64,
                "denies": 2,
                "gold_per_min": 293,
                "xp_per_min": 377,
                "level": 16,
                "net_worth": 3944,
                "aghanims_scepter": 0,
                "aghanims_shard": 0,
                "moonshard": 0,
                "hero_damage": 7721,
                "tower_damage": 22,
                "hero_healing": 195,
                "gold": 1419,
                "gold_spent": 8235,
                "scaled_hero_damage": 4993,
                "scaled_tower_damage": 18,
                "scaled_hero_healing": 89,
                "ability_upgrades": [
                    {
                        "ability": 5366,
                        "time": 138,
                        "level": 1
                    },
                    {
                        "ability": 5368,
                        "time": 384,
                        "level": 2
                    },
                    {
                        "ability": 5365,
                        "time": 426,
                        "level": 3
                    },
                    {
                        "ability": 5366,
                        "time": 526,
                        "level": 4
                    },
                    {
                        "ability": 5366,
                        "time": 693,
                        "level": 5
                    },
                    {
                        "ability": 5369,
                        "time": 826,
                        "level": 6
                    },
                    {
                        "ability": 5366,
                        "time": 980,
                        "level": 7
                    },
                    {
                        "ability": 5365,
                        "time": 1124,
                        "level": 8
                    },
                    {
                        "ability": 5365,
                        "time": 1348,
                        "level": 9
                    },
                    {
                        "ability": 6101,
                        "time": 1476,
                        "level": 10
                    },
                    {
                        "ability": 5368,
                        "time": 1610,
                        "level": 11
                    },
                    {
                        "ability": 5369,
                        "time": 1716,
                        "level": 12
                    },
                    {
                        "ability": 5365,
                        "time": 1878,
                        "level": 13
                    },
                    {
                        "ability": 5368,
                        "time": 2069,
                        "level": 14
                    },
                    {
                        "ability": 6195,
                        "time": 2111,
                        "level": 15
                    },
                    {
                        "ability": 5368,
                        "time": 2179,
                        "level": 16
                    }
                ]
            },
            {
                "account_id": 4294967295,
                "player_slot": 131,
                "team_number": 1,
                "team_slot": 3,
                "hero_id": 14,
                "item_0": 1,
                "item_1": 178,
                "item_2": 34,
                "item_3": 214,
                "item_4": 125,
                "item_5": 21,
                "backpack_0": 11,
                "backpack_1": 0,
                "backpack_2": 0,
                "item_neutral": 574,
                "kills": 2,
                "deaths": 12,
                "assists": 6,
                "leaver_status": 0,
                "last_hits": 71,
                "denies": 7,
                "gold_per_min": 261,
                "xp_per_min": 295,
                "level": 13,
                "net_worth": 7012,
                "aghanims_scepter": 0,
                "aghanims_shard": 0,
                "moonshard": 0,
                "hero_damage": 11671,
                "tower_damage": 0,
                "hero_healing": 0,
                "gold": 12,
                "gold_spent": 7735,
                "scaled_hero_damage": 6891,
                "scaled_tower_damage": 0,
                "scaled_hero_healing": 0,
                "ability_upgrades": [
                    {
                        "ability": 5075,
                        "time": 179,
                        "level": 1
                    },
                    {
                        "ability": 5076,
                        "time": 321,
                        "level": 2
                    },
                    {
                        "ability": 5074,
                        "time": 454,
                        "level": 3
                    },
                    {
                        "ability": 5076,
                        "time": 628,
                        "level": 4
                    },
                    {
                        "ability": 5076,
                        "time": 747,
                        "level": 5
                    },
                    {
                        "ability": 5077,
                        "time": 844,
                        "level": 6
                    },
                    {
                        "ability": 5076,
                        "time": 1026,
                        "level": 7
                    },
                    {
                        "ability": 5074,
                        "time": 1230,
                        "level": 8
                    },
                    {
                        "ability": 5074,
                        "time": 1323,
                        "level": 9
                    },
                    {
                        "ability": 5074,
                        "time": 1442,
                        "level": 10
                    },
                    {
                        "ability": 5075,
                        "time": 1472,
                        "level": 11
                    },
                    {
                        "ability": 5077,
                        "time": 1819,
                        "level": 12
                    },
                    {
                        "ability": 5075,
                        "time": 2073,
                        "level": 13
                    }
                ]
            },
            {
                "account_id": 4294967295,
                "player_slot": 132,
                "team_number": 1,
                "team_slot": 4,
                "hero_id": 42,
                "item_0": 116,
                "item_1": 65,
                "item_2": 151,
                "item_3": 50,
                "item_4": 1,
                "item_5": 168,
                "backpack_0": 0,
                "backpack_1": 0,
                "backpack_2": 0,
                "item_neutral": 573,
                "kills": 10,
                "deaths": 8,
                "assists": 3,
                "leaver_status": 0,
                "last_hits": 290,
                "denies": 4,
                "gold_per_min": 612,
                "xp_per_min": 699,
                "level": 22,
                "net_worth": 17167,
                "aghanims_scepter": 0,
                "aghanims_shard": 0,
                "moonshard": 0,
                "hero_damage": 22661,
                "tower_damage": 4243,
                "hero_healing": 0,
                "gold": 1167,
                "gold_spent": 18370,
                "scaled_hero_damage": 13119,
                "scaled_tower_damage": 1841,
                "scaled_hero_healing": 0,
                "ability_upgrades": [
                    {
                        "ability": 5086,
                        "time": 255,
                        "level": 1
                    },
                    {
                        "ability": 5087,
                        "time": 352,
                        "level": 2
                    },
                    {
                        "ability": 5087,
                        "time": 482,
                        "level": 3
                    },
                    {
                        "ability": 5088,
                        "time": 529,
                        "level": 4
                    },
                    {
                        "ability": 5087,
                        "time": 644,
                        "level": 5
                    },
                    {
                        "ability": 5088,
                        "time": 790,
                        "level": 6
                    },
                    {
                        "ability": 5088,
                        "time": 868,
                        "level": 7
                    },
                    {
                        "ability": 5088,
                        "time": 923,
                        "level": 8
                    },
                    {
                        "ability": 5918,
                        "time": 1037,
                        "level": 9
                    },
                    {
                        "ability": 5087,
                        "time": 1098,
                        "level": 10
                    },
                    {
                        "ability": 5089,
                        "time": 1175,
                        "level": 11
                    },
                    {
                        "ability": 5089,
                        "time": 1176,
                        "level": 12
                    },
                    {
                        "ability": 5086,
                        "time": 1183,
                        "level": 13
                    },
                    {
                        "ability": 5086,
                        "time": 1316,
                        "level": 14
                    },
                    {
                        "ability": 809,
                        "time": 1394,
                        "level": 15
                    },
                    {
                        "ability": 5086,
                        "time": 1472,
                        "level": 16
                    },
                    {
                        "ability": 5089,
                        "time": 1681,
                        "level": 17
                    },
                    {
                        "ability": 6801,
                        "time": 1963,
                        "level": 18
                    }
                ]
            }
        ],
        "radiant_win": true,
        "duration": 1968,
        "pre_game_duration": 90,
        "start_time": 1660051838,
        "match_id": 6699518234,
        "match_seq_num": 5604015962,
        "tower_status_radiant": 1847,
        "tower_status_dire": 288,
        "barracks_status_radiant": 63,
        "barracks_status_dire": 61,
        "cluster": 273,
        "first_blood_time": 18,
        "lobby_type": 7,
        "human_players": 10,
        "leagueid": 0,
        "positive_votes": 0,
        "negative_votes": 0,
        "game_mode": 22,
        "flags": 0,
        "engine": 1,
        "radiant_score": 49,
        "dire_score": 25,
        "picks_bans": [
            {
                "is_pick": true,
                "hero_id": 41,
                "team": 0,
                "order": 0
            },
            {
                "is_pick": true,
                "hero_id": 136,
                "team": 0,
                "order": 1
            },
            {
                "is_pick": true,
                "hero_id": 14,
                "team": 1,
                "order": 2
            },
            {
                "is_pick": true,
                "hero_id": 73,
                "team": 1,
                "order": 3
            },
            {
                "is_pick": true,
                "hero_id": 13,
                "team": 0,
                "order": 4
            },
            {
                "is_pick": true,
                "hero_id": 112,
                "team": 0,
                "order": 5
            },
            {
                "is_pick": true,
                "hero_id": 7,
                "team": 0,
                "order": 6
            },
            {
                "is_pick": true,
                "hero_id": 42,
                "team": 1,
                "order": 7
            },
            {
                "is_pick": true,
                "hero_id": 26,
                "team": 1,
                "order": 8
            },
            {
                "is_pick": true,
                "hero_id": 126,
                "team": 1,
                "order": 9
            },
            {
                "is_pick": true,
                "hero_id": 58,
                "team": 0,
                "order": 10
            },
            {
                "is_pick": false,
                "hero_id": 33,
                "team": 0,
                "order": 11
            },
            {
                "is_pick": false,
                "hero_id": 73,
                "team": 0,
                "order": 12
            },
            {
                "is_pick": false,
                "hero_id": 8,
                "team": 0,
                "order": 13
            },
            {
                "is_pick": false,
                "hero_id": 135,
                "team": 0,
                "order": 14
            },
            {
                "is_pick": false,
                "hero_id": 90,
                "team": 0,
                "order": 15
            }
        ]
    }
}